binary_extensions/__init__.py
binary_extensions/_data.py
binary_extensions/py.typed
binary_extensions-1.0.1.dist-info/METADATA
binary_extensions-1.0.1.dist-info/WHEEL
binary_extensions-1.0.1.dist-info/licenses/LICENSE
binary_extensions-1.0.1.dist-info/RECORD
