Metadata-Version: 2.4
Name: binary-extensions
Version: 1.0.1
Summary: Check if a file or extension is binary, and iterate over 250+ known binary file types including images, videos, archives, and executables. Python port of binary-extensions npm package.
Project-URL: Homepage, https://github.com/ysskrishna/binary-extensions
Project-URL: Repository, https://github.com/ysskrishna/binary-extensions.git
Project-URL: Issues, https://github.com/ysskrishna/binary-extensions/issues
Project-URL: Changelog, https://github.com/ysskrishna/binary-extensions/blob/main/CHANGELOG.md
Project-URL: Discussions, https://github.com/ysskrishna/binary-extensions/discussions
Author-email: ysskrishna <sivasaikrishnassk@gmail.com>
License: MIT
License-File: LICENSE
Keywords: binary,binary-detection,binary-files,extension,extensions,file,file-detection,file-extensions,file-type,file-utils,mime-type,mit license,utilities,utils,ysskrishna
Classifier: Development Status :: 5 - Production/Stable
Classifier: Intended Audience :: Developers
Classifier: License :: OSI Approved :: MIT License
Classifier: Operating System :: OS Independent
Classifier: Programming Language :: Python :: 3
Classifier: Programming Language :: Python :: 3.8
Classifier: Programming Language :: Python :: 3.9
Classifier: Programming Language :: Python :: 3.10
Classifier: Programming Language :: Python :: 3.11
Classifier: Programming Language :: Python :: 3.12
Classifier: Topic :: Software Development :: Libraries :: Python Modules
Classifier: Topic :: Utilities
Classifier: Typing :: Typed
Requires-Python: >=3.8
